Metadata-Version: 1.0
Name: mytestlib-ts
Version: 1.0.0
Summary: My Test Library.
Home-page: https://pypi.org/manage/projects/
Author: SeYaTa
Author-email: u84bc8fed7jvgE05SE@softbank.ne.jp
License: UNKNOWN
Platform: UNKNOWN
